{
  "standard": "ERG5-5",
  "title": "Engineering Recommendation G5/5 UK Harmonic Distortion Limits",
  "body": "ENA",
  "edition_latest": "latest as of 2026",
  "scope_one_line": "UK DNO limits on current and voltage harmonic distortion for connected installations",
  "jurisdiction": ["GB"],
  "status": "stub",
  "related_skills": ["power-quality-study (stub)"],
  "files_planned": [
    "terminology.md",
    "part-1-overview.json",
    "part-2-definitions.json",
    "tables-and-selection-data.json"
  ],
  "license_note": "Clause references + brief paraphrase only — never full standard text."
}
